{
    "Problem": [
        {
            "Lower bound": -80372.0,
            "Name": "tmpi8qo9yy4.pyomo",
            "Number of constraints": 253,
            "Number of nonzeros": 1291,
            "Number of objectives": 1,
            "Number of variables": 483,
            "Sense": "minimize",
            "Upper bound": -80372.0
        }
    ],
    "Solution": [
        {
            "number of solutions": 1,
            "number of solutions displayed": 1
        },
        {
            "Constraint": "No values",
            "Gap": 0.0,
            "Message": null,
            "Objective": {
                "OBJ": {
                    "Value": -80372
                }
            },
            "Problem": {},
            "Status": "optimal",
            "Variable": {
                "HA[1]": {
                    "Value": 40
                },
                "HA[2]": {
                    "Value": 50
                },
                "HA[3]": {
                    "Value": 60
                },
                "HA[4]": {
                    "Value": 650
                },
                "HA[5]": {
                    "Value": 430
                },
                "Ic[5,3]": {
                    "Value": 1
                },
                "Ic[5,5]": {
                    "Value": 1
                },
                "uc[1,1]": {
                    "Value": 2
                },
                "uc[1,2]": {
                    "Value": 30
                },
                "uc[2,1]": {
                    "Value": 20
                },
                "uc[2,2]": {
                    "Value": 30
                },
                "uc[2,3]": {
                    "Value": 360
                },
                "uc[3,2]": {
                    "Value": 30
                },
                "uc[4,1]": {
                    "Value": 20
                },
                "uc[4,2]": {
                    "Value": 30
                },
                "uc[5,1]": {
                    "Value": 20
                },
                "uc[5,2]": {
                    "Value": 3
                },
                "uc[6,1]": {
                    "Value": 20
                },
                "uc[6,2]": {
                    "Value": 30
                },
                "uc[7,2]": {
                    "Value": 30
                },
                "uf[1,1]": {
                    "Value": 200
                },
                "uf[1,2]": {
                    "Value": 264
                },
                "uf[1,3]": {
                    "Value": 400
                },
                "uf[1,4]": {
                    "Value": 500
                },
                "uf[1,5]": {
                    "Value": 600
                },
                "uf[2,1]": {
                    "Value": 200
                },
                "uf[2,2]": {
                    "Value": 300
                },
                "uf[2,3]": {
                    "Value": 400
                },
                "uf[2,4]": {
                    "Value": 500
                },
                "uf[2,5]": {
                    "Value": 600
                },
                "uf[3,1]": {
                    "Value": 200
                },
                "uf[3,2]": {
                    "Value": 300
                },
                "uf[3,3]": {
                    "Value": 400
                },
                "uf[3,4]": {
                    "Value": 500
                },
                "uf[3,5]": {
                    "Value": 600
                },
                "uf[4,1]": {
                    "Value": 200
                },
                "uf[4,2]": {
                    "Value": 300
                },
                "uf[4,3]": {
                    "Value": 400
                },
                "uf[4,4]": {
                    "Value": 500
                },
                "uf[4,5]": {
                    "Value": 600
                },
                "uf[5,1]": {
                    "Value": 200
                },
                "uf[5,2]": {
                    "Value": 265
                },
                "uf[5,3]": {
                    "Value": 354
                },
                "uf[5,4]": {
                    "Value": 500
                },
                "uf[5,5]": {
                    "Value": 547
                },
                "uf[6,1]": {
                    "Value": 200
                },
                "uf[6,2]": {
                    "Value": 300
                },
                "uf[6,3]": {
                    "Value": 400
                },
                "uf[6,4]": {
                    "Value": 500
                },
                "uf[6,5]": {
                    "Value": 600
                },
                "uf[7,1]": {
                    "Value": 200
                },
                "uf[7,2]": {
                    "Value": 300
                },
                "uf[7,3]": {
                    "Value": 400
                },
                "uf[7,4]": {
                    "Value": 500
                },
                "uf[7,5]": {
                    "Value": 546
                },
                "vc[1,3]": {
                    "Value": 4
                },
                "vc[1,4]": {
                    "Value": 50
                },
                "vc[1,5]": {
                    "Value": 60
                },
                "vc[2,3]": {
                    "Value": 40
                },
                "vc[2,4]": {
                    "Value": 50
                },
                "vc[2,5]": {
                    "Value": 60
                },
                "vc[3,3]": {
                    "Value": 40
                },
                "vc[3,4]": {
                    "Value": 50
                },
                "vc[3,5]": {
                    "Value": 60
                },
                "vc[4,3]": {
                    "Value": 40
                },
                "vc[4,4]": {
                    "Value": 50
                },
                "vc[4,5]": {
                    "Value": 60
                },
                "vc[5,3]": {
                    "Value": 4
                },
                "vc[5,4]": {
                    "Value": 5
                },
                "vc[5,5]": {
                    "Value": 6
                },
                "vc[6,3]": {
                    "Value": 40
                },
                "vc[6,4]": {
                    "Value": 50
                },
                "vc[6,5]": {
                    "Value": 60
                },
                "vc[7,3]": {
                    "Value": 40
                },
                "vc[7,4]": {
                    "Value": 50
                },
                "vc[7,5]": {
                    "Value": 6
                },
                "vf[1,2]": {
                    "Value": 36
                },
                "vf[5,2]": {
                    "Value": 35
                },
                "vf[5,3]": {
                    "Value": 46
                },
                "vf[5,5]": {
                    "Value": 53
                },
                "vf[7,5]": {
                    "Value": 54
                },
                "x[1,1]": {
                    "Value": 40
                },
                "x[1,2]": {
                    "Value": 50
                },
                "x[1,3]": {
                    "Value": 60
                },
                "x[1,4]": {
                    "Value": 650
                },
                "x[1,5]": {
                    "Value": 430
                },
                "x[2,1]": {
                    "Value": 40
                },
                "x[2,2]": {
                    "Value": 50
                },
                "x[2,3]": {
                    "Value": 60
                },
                "x[2,4]": {
                    "Value": 650
                },
                "x[2,5]": {
                    "Value": 430
                },
                "x[3,1]": {
                    "Value": 40
                },
                "x[3,2]": {
                    "Value": 50
                },
                "x[3,3]": {
                    "Value": 60
                },
                "x[3,4]": {
                    "Value": 650
                },
                "x[3,5]": {
                    "Value": 430
                },
                "x[4,1]": {
                    "Value": 40
                },
                "x[4,2]": {
                    "Value": 50
                },
                "x[4,3]": {
                    "Value": 60
                },
                "x[4,4]": {
                    "Value": 650
                },
                "x[4,5]": {
                    "Value": 430
                },
                "x[5,1]": {
                    "Value": 40
                },
                "x[5,2]": {
                    "Value": 50
                },
                "x[5,3]": {
                    "Value": 60
                },
                "x[5,4]": {
                    "Value": 650
                },
                "x[5,5]": {
                    "Value": 430
                },
                "x[6,1]": {
                    "Value": 40
                },
                "x[6,2]": {
                    "Value": 50
                },
                "x[6,3]": {
                    "Value": 60
                },
                "x[6,4]": {
                    "Value": 650
                },
                "x[6,5]": {
                    "Value": 430
                },
                "x[7,1]": {
                    "Value": 40
                },
                "x[7,2]": {
                    "Value": 50
                },
                "x[7,3]": {
                    "Value": 60
                },
                "x[7,4]": {
                    "Value": 650
                },
                "x[7,5]": {
                    "Value": 430
                },
                "xc[1,1]": {
                    "Value": 4
                },
                "xc[1,2]": {
                    "Value": 50
                },
                "xc[1,3]": {
                    "Value": 60
                },
                "xc[1,4]": {
                    "Value": 650
                },
                "xc[1,5]": {
                    "Value": 430
                },
                "xc[2,1]": {
                    "Value": 40
                },
                "xc[2,2]": {
                    "Value": 50
                },
                "xc[2,3]": {
                    "Value": 60
                },
                "xc[2,4]": {
                    "Value": 650
                },
                "xc[2,5]": {
                    "Value": 430
                },
                "xc[3,1]": {
                    "Value": 40
                },
                "xc[3,2]": {
                    "Value": 50
                },
                "xc[3,3]": {
                    "Value": 60
                },
                "xc[3,4]": {
                    "Value": 650
                },
                "xc[3,5]": {
                    "Value": 430
                },
                "xc[4,1]": {
                    "Value": 40
                },
                "xc[4,2]": {
                    "Value": 50
                },
                "xc[4,3]": {
                    "Value": 60
                },
                "xc[4,4]": {
                    "Value": 650
                },
                "xc[4,5]": {
                    "Value": 430
                },
                "xc[5,1]": {
                    "Value": 5
                },
                "xc[5,2]": {
                    "Value": 4
                },
                "xc[5,3]": {
                    "Value": 7
                },
                "xc[5,4]": {
                    "Value": 650
                },
                "xc[5,5]": {
                    "Value": 430
                },
                "xc[6,1]": {
                    "Value": 40
                },
                "xc[6,2]": {
                    "Value": 50
                },
                "xc[6,3]": {
                    "Value": 60
                },
                "xc[6,4]": {
                    "Value": 650
                },
                "xc[6,5]": {
                    "Value": 430
                },
                "xc[7,1]": {
                    "Value": 40
                },
                "xc[7,2]": {
                    "Value": 50
                },
                "xc[7,3]": {
                    "Value": 6
                },
                "xc[7,4]": {
                    "Value": 650
                },
                "xc[7,5]": {
                    "Value": 430
                },
                "xf[1,1,2]": {
                    "Value": 36
                },
                "xf[5,1,2]": {
                    "Value": 35
                },
                "xf[5,2,3]": {
                    "Value": 46
                },
                "xf[5,3,5]": {
                    "Value": 53
                },
                "xf[7,3,5]": {
                    "Value": 54
                },
                "z[1,1,1]": {
                    "Value": 1
                },
                "z[1,1,2]": {
                    "Value": 1
                },
                "z[1,1,3]": {
                    "Value": 1
                },
                "z[1,1,4]": {
                    "Value": 1
                },
                "z[1,1,5]": {
                    "Value": 126
                },
                "z[1,2,1]": {
                    "Value": 1
                },
                "z[1,2,2]": {
                    "Value": 12
                },
                "z[1,2,3]": {
                    "Value": 15
                },
                "z[1,2,4]": {
                    "Value": 1
                },
                "z[1,2,5]": {
                    "Value": 126
                },
                "z[1,3,1]": {
                    "Value": 1
                },
                "z[1,3,2]": {
                    "Value": 1
                },
                "z[1,3,3]": {
                    "Value": 1
                },
                "z[1,3,4]": {
                    "Value": 215
                },
                "z[1,3,5]": {
                    "Value": 122
                },
                "z[2,1,1]": {
                    "Value": 1
                },
                "z[2,1,2]": {
                    "Value": 1
                },
                "z[2,1,3]": {
                    "Value": 1
                },
                "z[2,1,4]": {
                    "Value": 1
                },
                "z[2,1,5]": {
                    "Value": 1
                },
                "z[2,2,1]": {
                    "Value": 1
                },
                "z[2,2,2]": {
                    "Value": 1
                },
                "z[2,2,3]": {
                    "Value": 1
                },
                "z[2,2,4]": {
                    "Value": 1
                },
                "z[2,2,5]": {
                    "Value": 1
                },
                "z[2,3,1]": {
                    "Value": 1
                },
                "z[2,3,2]": {
                    "Value": 17
                },
                "z[2,3,3]": {
                    "Value": 1
                },
                "z[2,3,4]": {
                    "Value": 1
                },
                "z[2,3,5]": {
                    "Value": 1
                },
                "z[3,1,1]": {
                    "Value": 1
                },
                "z[3,1,2]": {
                    "Value": 1
                },
                "z[3,1,3]": {
                    "Value": 1
                },
                "z[3,1,4]": {
                    "Value": 1
                },
                "z[3,1,5]": {
                    "Value": 1
                },
                "z[3,2,1]": {
                    "Value": 1
                },
                "z[3,2,2]": {
                    "Value": 1
                },
                "z[3,2,3]": {
                    "Value": 1
                },
                "z[3,2,4]": {
                    "Value": 1
                },
                "z[3,2,5]": {
                    "Value": 1
                },
                "z[3,3,1]": {
                    "Value": 1
                },
                "z[3,3,2]": {
                    "Value": 1
                },
                "z[3,3,3]": {
                    "Value": 1
                },
                "z[3,3,4]": {
                    "Value": 1
                },
                "z[3,3,5]": {
                    "Value": 1
                },
                "z[4,1,1]": {
                    "Value": 1
                },
                "z[4,1,2]": {
                    "Value": 1
                },
                "z[4,1,3]": {
                    "Value": 1
                },
                "z[4,1,4]": {
                    "Value": 1
                },
                "z[4,1,5]": {
                    "Value": 1
                },
                "z[4,2,1]": {
                    "Value": 1
                },
                "z[4,2,2]": {
                    "Value": 1
                },
                "z[4,2,3]": {
                    "Value": 1
                },
                "z[4,2,4]": {
                    "Value": 1
                },
                "z[4,2,5]": {
                    "Value": 1
                },
                "z[4,3,1]": {
                    "Value": 1
                },
                "z[4,3,2]": {
                    "Value": 1
                },
                "z[4,3,3]": {
                    "Value": 1
                },
                "z[4,3,4]": {
                    "Value": 1
                },
                "z[4,3,5]": {
                    "Value": 1
                },
                "ze[1,1,1]": {
                    "Value": 9
                },
                "ze[1,1,2]": {
                    "Value": 12
                },
                "ze[1,1,3]": {
                    "Value": 1
                },
                "ze[1,1,4]": {
                    "Value": 192
                },
                "ze[1,1,5]": {
                    "Value": 1
                },
                "ze[1,2,1]": {
                    "Value": 9
                },
                "ze[1,2,2]": {
                    "Value": 1
                },
                "ze[1,2,3]": {
                    "Value": 1
                },
                "ze[1,2,4]": {
                    "Value": 192
                },
                "ze[1,2,5]": {
                    "Value": 1
                },
                "ze[1,3,1]": {
                    "Value": 13
                },
                "ze[1,3,2]": {
                    "Value": 1
                },
                "ze[1,3,3]": {
                    "Value": 21
                },
                "ze[1,3,4]": {
                    "Value": 43
                },
                "ze[1,3,5]": {
                    "Value": 48
                },
                "ze[2,1,1]": {
                    "Value": 1
                },
                "ze[2,1,2]": {
                    "Value": 1
                },
                "ze[2,1,3]": {
                    "Value": 15
                },
                "ze[2,1,4]": {
                    "Value": 1
                },
                "ze[2,1,5]": {
                    "Value": 1
                },
                "ze[2,2,1]": {
                    "Value": 1
                },
                "ze[2,2,2]": {
                    "Value": 1
                },
                "ze[2,2,3]": {
                    "Value": 1
                },
                "ze[2,2,4]": {
                    "Value": 1
                },
                "ze[2,2,5]": {
                    "Value": 1
                },
                "ze[2,3,1]": {
                    "Value": 1
                },
                "ze[2,3,2]": {
                    "Value": 1
                },
                "ze[2,3,3]": {
                    "Value": 1
                },
                "ze[2,3,4]": {
                    "Value": 1
                },
                "ze[2,3,5]": {
                    "Value": 1
                },
                "ze[3,1,1]": {
                    "Value": 1
                },
                "ze[3,1,2]": {
                    "Value": 1
                },
                "ze[3,1,3]": {
                    "Value": 1
                },
                "ze[3,1,4]": {
                    "Value": 1
                },
                "ze[3,1,5]": {
                    "Value": 1
                },
                "ze[3,2,1]": {
                    "Value": 1
                },
                "ze[3,2,2]": {
                    "Value": 1
                },
                "ze[3,2,3]": {
                    "Value": 1
                },
                "ze[3,2,4]": {
                    "Value": 1
                },
                "ze[3,2,5]": {
                    "Value": 1
                },
                "ze[3,3,1]": {
                    "Value": 1
                },
                "ze[3,3,2]": {
                    "Value": 1
                },
                "ze[3,3,3]": {
                    "Value": 1
                },
                "ze[3,3,4]": {
                    "Value": 1
                },
                "ze[3,3,5]": {
                    "Value": 1
                },
                "ze[4,1,1]": {
                    "Value": 1
                },
                "ze[4,1,2]": {
                    "Value": 1
                },
                "ze[4,1,3]": {
                    "Value": 1
                },
                "ze[4,1,4]": {
                    "Value": 1
                },
                "ze[4,1,5]": {
                    "Value": 1
                },
                "ze[4,2,1]": {
                    "Value": 1
                },
                "ze[4,2,2]": {
                    "Value": 1
                },
                "ze[4,2,3]": {
                    "Value": 1
                },
                "ze[4,2,4]": {
                    "Value": 1
                },
                "ze[4,2,5]": {
                    "Value": 1
                },
                "ze[4,3,1]": {
                    "Value": 1
                },
                "ze[4,3,2]": {
                    "Value": 1
                },
                "ze[4,3,3]": {
                    "Value": 1
                },
                "ze[4,3,4]": {
                    "Value": 1
                },
                "ze[4,3,5]": {
                    "Value": 1
                }
            }
        }
    ],
    "Solver": [
        {
            "Error rc": 0,
            "Status": "ok",
            "Termination condition": "optimal",
            "Time": 0.37504029273986816,
            "User time": -1.0
        }
    ]
}